NextTestRunner/__init__.py
NextTestRunner/__main__.py
NextTestRunner/main.py
NextTestRunner/runner.py
NextTestRunner/bin/__init__.py
NextTestRunner/bin/conf/__init__.py
NextTestRunner/bin/conf/application.py
NextTestRunner/bin/conf/commandline.py
NextTestRunner/bin/conf/env.py
NextTestRunner/bin/conf/global_settings.py
NextTestRunner/bin/conf/html/__init__.py
NextTestRunner/bin/conf/html/email_test_template01.html
NextTestRunner/bin/conf/html/email_test_template02.html
NextTestRunner/bin/conf/html/email_test_template03.html
NextTestRunner/bin/conf/html/style_template.html
NextTestRunner/bin/conf/html/test_run_result_template01.html
NextTestRunner/components/__init__.py
NextTestRunner/components/_email.py
NextTestRunner/components/htmlRunner.py
NextTestRunner/components/htmlTestRunner-test1.py
NextTestRunner/support/__init__.py
NextTestRunner/support/common.py
NextTestRunner/support/logger_v2.py
NextTestRunner/support/system.py
bin/__init__.py
bin/conf/__init__.py
bin/conf/application.py
bin/conf/commandline.py
bin/conf/env.py
bin/conf/global_settings.py
components/__init__.py
components/_email.py
components/htmlRunner.py
components/htmlTestRunner-test1.py
support/__init__.py
support/common.py
support/logger_v2.py
support/system.py
NextTestRunner-0.0.5.dist-info/LICENSE
NextTestRunner-0.0.5.dist-info/METADATA
NextTestRunner-0.0.5.dist-info/WHEEL
NextTestRunner-0.0.5.dist-info/top_level.txt
NextTestRunner-0.0.5.dist-info/RECORD
