Metadata-Version: 2.1
Name: NextTestRunner
Version: 0.0.5
Summary: 新一代，自动化测试执行器
Home-page: https://github.com/gfl13453001/NextTestRunner
Author: guanfl
Author-email: gfl13453001@163.com
License: UNKNOWN
Keywords: sveltest linux python selenium unittest
Platform: UNKNOWN
Classifier: Development Status :: 4 - Beta
Classifier: Programming Language :: Python :: 3.6
Classifier: Programming Language :: Python :: 3.7
Classifier: Programming Language :: Python :: 3.8
Classifier: License :: OSI Approved :: MIT License
Classifier: Operating System :: OS Independent
Requires-Python: >=3.7
Requires-Dist: rich
Requires-Dist: jinja2
Requires-Dist: pyyaml
Requires-Dist: loguru (==0.6.0)
Requires-Dist: yagmail
